asyncselenium/__init__.py
asyncselenium/common/__init__.py
asyncselenium/common/async_alert.py
asyncselenium/webdriver/__init__.py
asyncselenium/webdriver/chrome/__init__.py
asyncselenium/webdriver/chrome/async_remote_connection.py
asyncselenium/webdriver/chrome/async_webdriver.py
asyncselenium/webdriver/remote/__init__.py
asyncselenium/webdriver/remote/async_mobile.py
asyncselenium/webdriver/remote/async_object.py
asyncselenium/webdriver/remote/async_remote_connection.py
asyncselenium/webdriver/remote/async_swith_to.py
asyncselenium/webdriver/remote/async_webdriver.py
asyncselenium/webdriver/remote/async_webelement.py
asyncselenium/webdriver/support/__init__.py
asyncselenium/webdriver/support/async_expected_conditions.py
asyncselenium/webdriver/support/async_select.py
asyncselenium/webdriver/support/async_wait.py
asyncselenium-0.0.2.dist-info/LICENSE
asyncselenium-0.0.2.dist-info/METADATA
asyncselenium-0.0.2.dist-info/WHEEL
asyncselenium-0.0.2.dist-info/top_level.txt
asyncselenium-0.0.2.dist-info/RECORD
